s3_website/S3WebsiteConfig.py
s3_website/__init__.py
s3_website/cfcreate.py
s3_website/cfdelete.py
s3_website/cfupdate.py
s3_website/command_runner.py
s3_website/create.py
s3_website/delete.py
s3_website/exitcodes.py
s3_website/helper.py
s3_website/information.py
s3_website/log.py
s3_website/main.py
s3_website/pkginfo.py
s3_website/update.py
s3_website/version.py
s3_website/tests/__init__.py
s3_website/tests/test_helper.py
s3_cmd_website-0.6.0.dist-info/top_level.txt
s3_cmd_website-0.6.0.dist-info/entry_points.txt
s3_cmd_website-0.6.0.dist-info/METADATA
s3_cmd_website-0.6.0.dist-info/DESCRIPTION.rst
s3_cmd_website-0.6.0.dist-info/metadata.json
s3_cmd_website-0.6.0.dist-info/WHEEL
s3_cmd_website-0.6.0.dist-info/RECORD
