Metadata-Version: 2.0
Name: s3-cmd-website
Version: 0.6.0
Summary: Wrapper around s3cmd for creating, deploying, updating and deleting websites hosted in s3
Home-page: http://github.com/theidledeveloper/s3_cmd_website
Author: TheIdleDeveloper
Author-email: TheIdleDeveloper@gmail.com
License: MIT
Download-URL: https://github.com/TheIdleDeveloper/s3_cmd_website/tarball/0.6.0
Keywords: s3,aws,static website
Platform: UNKNOWN
Classifier: Development Status :: 4 - Beta
Classifier: Intended Audience :: Developers
Classifier: License :: OSI Approved :: MIT License
Classifier: Programming Language :: Python :: 2.7
Classifier: Programming Language :: Python :: 3.5
Classifier: Topic :: Internet :: WWW/HTTP :: Site Management
Requires-Dist: six
Requires-Dist: pyaml
Requires-Dist: s3cmd
